npchessimage/README.MD
npchessimage/__init__.py
npchessimage/requirements.txt
npchessimage/thirdparty.json
npchessimage-0.10.dist-info/LICENSE.rst
npchessimage-0.10.dist-info/METADATA
npchessimage-0.10.dist-info/WHEEL
npchessimage-0.10.dist-info/top_level.txt
npchessimage-0.10.dist-info/RECORD
