Metadata-Version: 2.1
Name: npchessimage
Version: 0.10
Summary: Creates a chessboard pattern as an image.
Home-page: https://github.com/hansalemaos/npchessimage
Author: Johannes Fischer
Author-email: aulasparticularesdealemaosp@gmail.com
License: MIT
Keywords: chessboard,image,numpy
Classifier: Development Status :: 4 - Beta
Classifier: Programming Language :: Python :: 3 :: Only
Classifier: Programming Language :: Python :: 3.10
Classifier: Topic :: Software Development :: Libraries :: Python Modules
Classifier: Topic :: Utilities
License-File: LICENSE.rst
Requires-Dist: numpy
